{"peoples":[{"id":40316,"name":"Jeremy Schumm","jobs":"igazgató"},{"id":44530,"name":"Tremaine VonRueden","jobs":"ügyintéző"},{"id":65711,"name":"Everardo Hackett","jobs":"igazgató"},{"id":6420,"name":"Albina Harber","jobs":"igazgató"},{"id":93815,"name":"Clara Satterfield","jobs":"ügyintéző"}],"appointments":[{"id":"1486","cases":"Birth certificate","dates":"2020-5-4","times":"16:00"},{"id":"4227","cases":"Renew driving licence","dates":"2020-5-4","times":"16:00"},{"id":"82516","cases":"Birth certificate","dates":"2020-5-4","times":"12:00"},{"id":"21265","cases":"Renew driving licence","dates":"2020-5-4","times":"9:00"},{"id":"17320","cases":"Get Married","dates":"2020-5-4","times":"16:00"}]}